data_science_pipeline_automation/__init__.py
data_science_pipeline_automation/eda.py
data_science_pipeline_automation/ml.py
data_science_pipeline_automation/preprocess.py
data_science_pipeline_automation/logic/__init__.py
data_science_pipeline_automation/logic/eda/__init__.py
data_science_pipeline_automation/logic/eda/check/__init__.py
data_science_pipeline_automation/logic/eda/check/alert.py
data_science_pipeline_automation/logic/eda/check/api.py
data_science_pipeline_automation/logic/eda/check/stat_calculator.py
data_science_pipeline_automation/logic/eda/load/__init__.py
data_science_pipeline_automation/logic/eda/load/df_dict_loader.py
data_science_pipeline_automation/logic/eda/load/pandas_csv.py
data_science_pipeline_automation/logic/eda/utils/__init__.py
data_science_pipeline_automation/logic/eda/utils/subprocess_wrapper.py
data_science_pipeline_automation/logic/eda/vis/__init__.py
data_science_pipeline_automation/logic/eda/vis/binned_bar.py
data_science_pipeline_automation/logic/eda/vis/binning.py
data_science_pipeline_automation/logic/eda/vis/histogram.py
data_science_pipeline_automation/logic/eda/vis/scatter.py
data_science_pipeline_automation/logic/ml/__init__.py
data_science_pipeline_automation/logic/ml/sklearn_cv_pandas/__init__.py
data_science_pipeline_automation/logic/ml/sklearn_cv_pandas/model.py
data_science_pipeline_automation/logic/ml/sklearn_cv_pandas/pandas_cv.py
data_science_pipeline_automation/logic/ml/tuner/__init__.py
data_science_pipeline_automation/logic/ml/tuner/cv_analyzer.py
data_science_pipeline_automation/logic/ml/tuner/ml_tuner.py
data_science_pipeline_automation/logic/ml/tuner/tuner_config/__init__.py
data_science_pipeline_automation/logic/ml/tuner/tuner_config/base.py
data_science_pipeline_automation/logic/ml/tuner/tuner_config/lightgbm.py
data_science_pipeline_automation/logic/ml/tuner/tuner_config/linear_model.py
data_science_pipeline_automation/logic/ml/tuner/tuner_config/random_forest.py
data_science_pipeline_automation-0.0.2.dist-info/LICENSE
data_science_pipeline_automation-0.0.2.dist-info/METADATA
data_science_pipeline_automation-0.0.2.dist-info/WHEEL
data_science_pipeline_automation-0.0.2.dist-info/top_level.txt
data_science_pipeline_automation-0.0.2.dist-info/RECORD
