Metadata-Version: 2.1
Name: data-science-pipeline-automation
Version: 0.0.2
Summary: Python library to help you to automate the data science pipeline
Home-page: https://github.com/chizhangucb/data_science_pipeline_automation
Author: @chizhangucb
Author-email: chizhangucb@gmail.com
License: UNKNOWN
Platform: UNKNOWN
Classifier: Programming Language :: Python :: 3
Classifier: License :: OSI Approved :: MIT License
Classifier: Operating System :: OS Independent
Requires-Python: >=3.6
Requires-Dist: pandas (>=1.1)
Requires-Dist: numpy
Requires-Dist: scipy
Requires-Dist: sklearn
Requires-Dist: altair
Requires-Dist: IPython
Requires-Dist: lightgbm
Requires-Dist: xgboost
Requires-Dist: gbm-autosplit (>=0.0.2)
Requires-Dist: networkx
